odoo/addons/contract_sale_invoicing_pricelist/README.rst
odoo/addons/contract_sale_invoicing_pricelist/__init__.py
odoo/addons/contract_sale_invoicing_pricelist/__manifest__.py
odoo/addons/contract_sale_invoicing_pricelist/i18n/contract_sale_invoicing_pricelist.pot
odoo/addons/contract_sale_invoicing_pricelist/i18n/it.po
odoo/addons/contract_sale_invoicing_pricelist/models/__init__.py
odoo/addons/contract_sale_invoicing_pricelist/models/contract.py
odoo/addons/contract_sale_invoicing_pricelist/readme/CONTRIBUTORS.rst
odoo/addons/contract_sale_invoicing_pricelist/readme/CREDITS.rst
odoo/addons/contract_sale_invoicing_pricelist/readme/DESCRIPTION.rst
odoo/addons/contract_sale_invoicing_pricelist/static/description/icon.png
odoo/addons/contract_sale_invoicing_pricelist/static/description/index.html
odoo/addons/contract_sale_invoicing_pricelist/tests/__init__.py
odoo/addons/contract_sale_invoicing_pricelist/tests/test_contract.py
odoo_addon_contract_sale_invoicing_pricelist-16.0.1.0.0.5.dist-info/METADATA
odoo_addon_contract_sale_invoicing_pricelist-16.0.1.0.0.5.dist-info/WHEEL
odoo_addon_contract_sale_invoicing_pricelist-16.0.1.0.0.5.dist-info/top_level.txt
odoo_addon_contract_sale_invoicing_pricelist-16.0.1.0.0.5.dist-info/RECORD
