Metadata-Version: 2.1
Name: odoo-addon-contract_sale_invoicing_pricelist
Version: 16.0.1.0.0.5
Summary: This module will set the invoice pricelist and currency based on the contract.
Home-page: https://github.com/OCA/contract
Author: BizzAppDev Systems Pvt. Ltd., Odoo Community Association (OCA)
Author-email: support@odoo-community.org
License: AGPL-3
Classifier: Programming Language :: Python
Classifier: Framework :: Odoo
Classifier: Framework :: Odoo :: 16.0
Classifier: License :: OSI Approved :: GNU Affero General Public License v3
Classifier: Development Status :: 3 - Alpha
Requires-Python: >=3.10
Requires-Dist: odoo-addon-account-invoice-pricelist<16.1dev,>=16.0dev
Requires-Dist: odoo-addon-contract<16.1dev,>=16.0dev
Requires-Dist: odoo<16.1dev,>=16.0a
